scanpy_mcp/__init__.py
scanpy_mcp/cli.py
scanpy_mcp/schema/__init__.py
scanpy_mcp/schema/util.py
scanpy_mcp/server/__init__.py
scanpy_mcp/server/util.py
scanpy_mcp-0.5.0.dist-info/METADATA
scanpy_mcp-0.5.0.dist-info/WHEEL
scanpy_mcp-0.5.0.dist-info/entry_points.txt
scanpy_mcp-0.5.0.dist-info/licenses/LICENSE
scanpy_mcp-0.5.0.dist-info/RECORD
