Metadata-Version: 2.4
Name: scanpy-mcp
Version: 0.5.0
Summary: Natural language interface for scRNA-Seq analysis with Scanpy through MCP.
Project-URL: Homepage, http://scmcphub.org/
Project-URL: Repository, https://github.com/scmcphub/scanpy-mcp
Project-URL: Documentation, https://docs.scmcphub.org/
Author-email: shuang <hsh-me@outlook.com>
License-File: LICENSE
Keywords: AI,agent,bioinformatics,llm,mcp,model context protocol,scRNA-seq,single cell
Requires-Python: >=3.10
Requires-Dist: agno
Requires-Dist: fastmcp>=2.3.5
Requires-Dist: igraph
Requires-Dist: lancedb
Requires-Dist: leidenalg
Requires-Dist: nest-asyncio
Requires-Dist: scanpy>=1.10.0
Requires-Dist: scmcp-shared>=0.3.5
